algo_bus/__init__.py
algo_bus/logger.py
algo_bus/api/__init__.py
algo_bus/api/algo_bus_api.py
algo_bus/dtp/Quotation_pb2.py
algo_bus/dtp/__init__.py
algo_bus/dtp/api_pb2.py
algo_bus/dtp/type_pb2.py
algo_bus/model/__init__.py
algo_bus/model/enum_class.py
algo_bus/model/instruction.py
algo_bus/model/order.py
algo_bus/spi/__init__.py
algo_bus/spi/algo_bus_spi.py
algo_bus/utils/__init__.py
algo_bus/utils/message_utils.py
algo_bus/ws/__init__.py
algo_bus/ws/websocket_client.py
algo_bus_sdk-0.0.9.dist-info/METADATA
algo_bus_sdk-0.0.9.dist-info/WHEEL
algo_bus_sdk-0.0.9.dist-info/top_level.txt
algo_bus_sdk-0.0.9.dist-info/RECORD
