Metadata-Version: 2.1
Name: algo-bus-sdk
Version: 0.0.9
Summary: YunChi Algo Bus SDK
Author: dwzx
Author-email: yunchi@idwzx.com
Classifier: Programming Language :: Python
Classifier: Programming Language :: Python :: 3.8
Requires-Dist: six (==1.16.0)
Requires-Dist: websocket-client (==1.2.3)
Requires-Dist: protobuf (==3.17.3)
Requires-Dist: pyzmq (==19.0.2)
Requires-Dist: requests (==2.26.0)
Requires-Dist: Cython (==0.29.25)
Requires-Dist: PyYAML (==6.0)
Requires-Dist: Logbook (==1.5.3)
